{
    "version": 2,
    "name": "1",
    "inherits": "fdmextruder",
    "metadata":
    {
        "machine": "ord",
        "position": "1"
    },
    "overrides":
    {
        "extruder_nr":
        {
            "default_value": 1,
            "maximum_value": "4"
        },
        "machine_nozzle_offset_x": { "default_value": 62.95 },
        "machine_nozzle_offset_y": { "default_value": 2.05 },
        "machine_nozzle_size": { "default_value": 0.35 },
        "material_diameter": { "default_value": 1.75 }
    }
}