{
    "id": "ord_extruder_3",
    "version": 2,
    "name": "3",
    "inherits": "fdmextruder",
    "metadata": {
        "machine": "ord",
        "position": "3"
    },

    "overrides": {
        "extruder_nr": {
            "default_value": 3,
            "maximum_value": "4"
        },
        "machine_nozzle_offset_x": { "default_value": 63.18 },
        "machine_nozzle_offset_y": { "default_value": 28.65 },
        "machine_nozzle_size": { "default_value": 0.35 },
        "material_diameter": { "default_value": 1.75 }
    }
}
