{
    "metadata": {
        "name": "Green",
        "inherits": "cura"
    },
    "colors": {
        "sidebar": [255, 255, 255, 255],
        "lining": [127, 127, 127, 255],
        "viewport_overlay": [24, 77, 41, 255],

        "primary": [12, 220, 164, 255],
        "primary_hover": [48, 231, 182, 255],
        "primary_text": [255, 255, 255, 255],
        "border": [127, 127, 127, 255],
        "secondary": [245, 245, 245, 255],

        "text": [24, 77, 41, 255],
        "text_detail": [174, 174, 174, 128],
        "text_link": [12, 220, 164, 255],
        "text_inactive": [174, 174, 174, 255],
        "text_hover": [70, 113, 84, 255],
        "text_pressed": [12, 220, 164, 255],
        "text_reversed": [255, 255, 255, 255],
        "text_subtext": [70, 113, 84, 255],

        "error": [255, 0, 140, 255],
        "sidebar_header_bar": [24, 77, 41, 255],
        "sidebar_header_active": [70, 113, 84, 255],
        "sidebar_header_hover": [24, 77, 41, 255],
        "sidebar_header_highlight": [12, 220, 164, 255],
        "sidebar_header_highlight_hover": [255, 255, 255, 255],
        "sidebar_lining": [245, 245, 245, 255],

        "button": [24, 77, 41, 255],
        "button_hover": [70, 113, 84, 255],
        "button_active": [32, 219, 166, 255],
        "button_active_hover": [12, 220, 164, 255],
        "button_text": [255, 255, 255, 255],
        "button_disabled": [24, 77, 41, 255],
        "button_disabled_text": [70, 113, 84, 255],

        "button_tooltip": [255, 255, 255, 255],
        "button_tooltip_border": [24, 77, 41, 255],
        "button_tooltip_text": [24, 77, 41, 255],

        "toggle_checked": [24, 77, 41, 255],
        "toggle_checked_border": [24, 77, 41, 255],
        "toggle_checked_text": [255, 255, 255, 255],
        "toggle_unchecked": [255, 255, 255, 255],
        "toggle_unchecked_border": [127, 127, 127, 255],
        "toggle_unchecked_text": [24, 77, 41, 255],
        "toggle_hovered": [255, 255, 255, 255],
        "toggle_hovered_border": [32, 219, 166, 255],
        "toggle_hovered_text": [24, 77, 41, 255],
        "toggle_active": [32, 219, 166, 255],
        "toggle_active_border": [32, 219, 166, 255],
        "toggle_active_text": [24, 77, 41, 255],

        "tab_checked": [255, 255, 255, 255],
        "tab_checked_border": [255, 255, 255, 255],
        "tab_checked_text": [24, 77, 41, 255],
        "tab_unchecked": [245, 245, 245, 255],
        "tab_unchecked_border": [245, 245, 245, 255],
        "tab_unchecked_text": [127, 127, 127, 255],
        "tab_hovered": [245, 245, 245, 255],
        "tab_hovered_border": [245, 245, 245, 255],
        "tab_hovered_text": [32, 219, 166, 255],
        "tab_active": [255, 255, 255, 255],
        "tab_active_border": [255, 255, 255, 255],
        "tab_active_text": [24, 77, 41, 255],
        "tab_background": [245, 245, 245, 255],

        "action_button": [255, 255, 255, 255],
        "action_button_text": [24, 77, 41, 255],
        "action_button_border": [127, 127, 127, 255],
        "action_button_hovered": [255, 255, 255, 255],
        "action_button_hovered_text": [24, 77, 41, 255],
        "action_button_hovered_border": [12, 220, 164, 255],
        "action_button_active": [12, 220, 164, 255],
        "action_button_active_text": [255, 255, 255, 255],
        "action_button_active_border": [12, 220, 164, 255],
        "action_button_disabled": [245, 245, 245, 255],
        "action_button_disabled_text": [127, 127, 127, 255],
        "action_button_disabled_border": [245, 245, 245, 255],

        "scrollbar_background": [255, 255, 255, 255],
        "scrollbar_handle": [24, 77, 41, 255],
        "scrollbar_handle_hover": [12, 227, 159, 255],
        "scrollbar_handle_down": [12, 227, 159, 255],

        "setting_category": [245, 245, 245, 255],
        "setting_category_disabled": [255, 255, 255, 255],
        "setting_category_hover": [245, 245, 245, 255],
        "setting_category_active": [245, 245, 245, 255],
        "setting_category_active_hover": [245, 245, 245, 255],
        "setting_category_text": [24, 77, 41, 255],
        "setting_category_border": [245, 245, 245, 255],
        "setting_category_disabled_border": [245, 245, 245, 255],
        "setting_category_hover_border": [12, 227, 159, 255],
        "setting_category_active_border": [245, 245, 245, 255],
        "setting_category_active_hover_border": [12, 227, 159, 255],

        "setting_control": [255, 255, 255, 255],
        "setting_control_selected": [24, 77, 41, 255],
        "setting_control_highlight": [255, 255, 255, 0],
        "setting_control_border": [127, 127, 127, 255],
        "setting_control_border_highlight": [12, 220, 164, 255],
        "setting_control_text": [24, 77, 41, 255],
        "setting_control_depth_line": [127, 127, 127, 255],
        "setting_control_button": [127, 127, 127, 255],
        "setting_control_button_hover": [70, 113, 84, 255],
        "setting_control_disabled": [245, 245, 245, 255],
        "setting_control_disabled_text": [127, 127, 127, 255],
        "setting_control_disabled_border": [127, 127, 127, 255],
        "setting_unit": [127, 127, 127, 255],

        "progressbar_background": [245, 245, 245, 255],
        "progressbar_control": [24, 77, 41, 255],

        "slider_groove": [245, 245, 245, 255],
        "slider_groove_border": [127, 127, 127, 255],
        "slider_groove_fill": [127, 127, 127, 255],
        "slider_handle": [32, 219, 166, 255],
        "slider_handle_hover": [77, 226, 182, 255],
        "slider_text_background": [255, 255, 255, 255],

        "checkbox": [255, 255, 255, 255],
        "checkbox_hover": [255, 255, 255, 255],
        "checkbox_border": [127, 127, 127, 255],
        "checkbox_border_hover": [12, 220, 164, 255],
        "checkbox_mark": [24, 77, 41, 255],
        "checkbox_text": [24, 77, 41, 255],

        "mode_switch": [255, 255, 255, 255],
        "mode_switch_hover": [255, 255, 255, 255],
        "mode_switch_border": [127, 127, 127, 255],
        "mode_switch_border_hover": [12, 220, 164, 255],
        "mode_switch_handle": [24, 77, 41, 255],
        "mode_switch_text": [24, 77, 41, 255],
        "mode_switch_text_hover": [24, 77, 41, 255],
        "mode_switch_text_checked": [12, 220, 164, 255],

        "tooltip": [12, 220, 164, 255],
        "tooltip_text": [255, 255, 255, 255],

        "message_background": [24, 77, 41, 255],
        "message_text": [255, 255, 255, 255],
        "message_border": [24, 77, 41, 255],
        "message_button": [255, 255, 255, 255],
        "message_button_hover": [12, 220, 164, 255],
        "message_button_active": [32, 219, 166, 255],
        "message_button_text": [24, 77, 41, 255],
        "message_button_text_hover": [255, 255, 255, 255],
        "message_button_text_active": [255, 255, 255, 255],
        "message_progressbar_background": [255, 255, 255, 255],
        "message_progressbar_control": [12, 220, 164, 255],

        "tool_panel_background": [255, 255, 255, 255],

        "disabled_axis": [127, 127, 127, 255],
        "x_axis": [255, 0, 0, 255],
        "y_axis": [0, 0, 255, 255],
        "z_axis": [0, 255, 0, 255],
        "all_axis": [255, 255, 255, 255],

        "viewport_background": [245, 245, 245, 255],
        "volume_outline": [12, 220, 164, 255],
        "buildplate": [244, 244, 244, 255],
        "buildplate_alt": [204, 204, 204, 255],

        "convex_hull": [35, 35, 35, 127],
        "disallowed_area": [0, 0, 0, 40],
        "error_area": [255, 0, 0, 127],

        "model_default": [255, 36, 201, 255],
        "model_selection_outline": [12, 220, 164, 255],

        "xray": [26, 62, 26, 255]
    }
}
