{
    "id": "blackbelt",
    "version": 2,
    "name": "BLACKBELT 3D Printer",
    "inherits": "fdmprinter",
    "metadata": {
        "visible": true,
        "author": "fieldOfView",
        "manufacturer": "BlackBelt 3D B.V.",
        "category": "BLACKBELT 3D",
        "platform": "blackbelt_platform.stl",
        "platform_offset": [0, -2, 0],
        "limit_buildvolume":
        {
            "depth":
            {
                "maximum": 320
            }
        },
        "has_machine_quality": true,
        "preferred_quality_type": "normal",
        "has_machine_materials": true,
        "preferred_material": "blackbelt_ngen",
        "limit_materials": ["generic_pla_175", "blackbelt_ngen", "blackbelt_ht"],
        "has_variants": true,
        "preferred_variant_name": "0.4 mm, 45°",
        "variants_id_pattern": "{definition_id}_{term}_{term}",
        "variants_name": "Configuration",
        "variants_terms":
        [
            {
                "name": "Gantry Angle",
                "values": {
                    "15": "15°",
                    "25": "25°",
                    "35": "35°",
                    "45": "45°"
                }
            },
            {
                "name": "Nozzle Size",
                "values": {
                    "0.4": "0.4 mm",
                    "0.6": "0.6 mm",
                    "0.8": "0.8 mm"
                }
            }
        ],
        "supported_actions": ["UpgradeFirmware"],
        "file_formats": "text/x-gcode"
    },

    "settings": {
        "blackbelt_settings": {
            "label": "BlackBelt",
            "type": "category",
            "description": "BlackBelt specific settings",
            "icon": "category_machine",
            "children":
            {
                "blackbelt_repetitions":
                {
                    "label": "Copies",
                    "description": "The number of times the objects on the build plate are printed. Note that the repetitions will not be visible in Layer View.",
                    "type": "int",
                    "minimum_value": "1",
                    "default_value": 1,
                    "settable_per_mesh": false,
                    "settable_per_extruder": false
                },
                "blackbelt_repetitions_distance":
                {
                    "label": "Distance Between Copies",
                    "description": "The distance the belt moves between repetitions.",
                    "type": "float",
                    "minimum_value": "0",
                    "default_value": 300,
                    "enabled": "blackbelt_repetitions > 1",
                    "settable_per_mesh": false,
                    "settable_per_extruder": false
                },
                "blackbelt_raft":
                {
                    "label": "Print Raft",
                    "description": "Adds a thick layer below the model to help the adhesion to the belt and to improve stability during printing.",
                    "type": "bool",
                    "default_value": false,
                    "settable_per_mesh": false,
                    "settable_per_extruder": false
                },
                "blackbelt_raft_thickness":
                {
                    "label": "Raft Thickness",
                    "description": "Layer thickness of the base raft layer. This should be a thick layer which sticks firmly to the printer build plate.",
                    "unit": "mm",
                    "type": "float",
                    "default_value": 0.8,
                    "value": "2 * line_width",
                    "minimum_value": "line_width",
                    "minimum_value_warning": "2 * line_width",
                    "enabled": "blackbelt_raft",
                    "settable_per_mesh": false,
                    "settable_per_extruder": false
                },
                "blackbelt_raft_gap":
                {
                    "label": "Raft Air Gap",
                    "description": "The gap between the raft and the bottom wall of the model. Makes it easier to peel off the raft.",
                    "unit": "mm",
                    "type": "float",
                    "default_value": 0.3,
                    "value": "0.75 * line_width",
                    "minimum_value": "0",
                    "maximum_value_warning": "min(extruderValues('machine_nozzle_size'))",
                    "enabled": "blackbelt_raft",
                    "settable_per_mesh": false,
                    "settable_per_extruder": false
                },
                "blackbelt_raft_speed":
                {
                    "label": "Raft Speed",
                    "description": "The speed at which the raft is printed. Printing the raft at a lower speed improves adhesion.",
                    "type": "float",
                    "unit": "mm/s",
                    "minimum_value": "0.1",
                    "maximum_value": "math.sqrt(machine_max_feedrate_x ** 2 + machine_max_feedrate_y ** 2)",
                    "maximum_value_warning": "150",
                    "default_value": 30,
                    "value": "speed_wall_0 * 0.6",
                    "enabled": "blackbelt_raft",
                    "settable_per_mesh": false,
                    "settable_per_extruder": false
                },
                "blackbelt_raft_flow":
                {
                    "label": "Raft Flow",
                    "description": "The extrusion multiplier for the raft.",
                    "type": "float",
                    "unit": "%",
                    "minimum_value": "5",
                    "minimum_value_warning": "50",
                    "maximum_value_warning": "150",
                    "default_value": 100,
                    "value": "material_flow",
                    "enabled": "blackbelt_raft",
                    "settable_per_mesh": false,
                    "settable_per_extruder": false
                },
                "blackbelt_belt_wall_enabled":
                {
                    "label": "Adjust Belt Wall",
                    "description": "Adjust settings for the wall touching the belt.",
                    "type": "bool",
                    "default_value": false,
                    "enabled": "not blackbelt_raft",
                    "settable_per_mesh": false,
                    "settable_per_extruder": false
                },
                "blackbelt_belt_wall_speed":
                {
                    "label": "Belt Wall Speed",
                    "description": "The speed at which the walls touching the belt are printed. Printing the belt layer at a lower speed improves adhesion.",
                    "type": "float",
                    "unit": "mm/s",
                    "minimum_value": "0.1",
                    "maximum_value": "math.sqrt(machine_max_feedrate_x ** 2 + machine_max_feedrate_y ** 2)",
                    "maximum_value_warning": "150",
                    "default_value": 30,
                    "value": "speed_wall_0 * 0.6",
                    "enabled": "blackbelt_belt_wall_enabled and not blackbelt_raft",
                    "settable_per_mesh": false,
                    "settable_per_extruder": false
                },
                "blackbelt_belt_wall_flow":
                {
                    "label": "Belt Wall Flow",
                    "description": "The extrusion multiplier for the walls touching the belt.",
                    "type": "float",
                    "unit": "%",
                    "minimum_value": "5",
                    "minimum_value_warning": "50",
                    "maximum_value_warning": "150",
                    "default_value": 100,
                    "value": "material_flow",
                    "enabled": "blackbelt_belt_wall_enabled and not blackbelt_raft",
                    "settable_per_mesh": false,
                    "settable_per_extruder": false
                },
                "blackbelt_z_offset_gap":
                {
                    "label": "Belt Offset",
                    "description": "The distance between the part and the conveyor belt. Adjust the gap to the belt to control adhesion between the print and the belt. Smaller gap means more adhesion, a bigger gap means less adhesion.",
                    "type": "float",
                    "unit": "mm",
                    "default_value": 0.2,
                    "minimum_value": "0",
                    "maximum_value": "5",
                    "settable_per_mesh": false,
                    "settable_per_extruder": false
                },
                "blackbelt_secondary_fans_enabled":
                {
                    "label": "Enable Secondary Print Fans",
                    "description": "Enables the secondary print cooling fans while printing.",
                    "type": "bool",
                    "enabled": "cool_fan_enabled",
                    "default_value": false,
                    "settable_per_mesh": false,
                    "settable_per_extruder": true
                },
                "blackbelt_secondary_fans_speed":
                {
                    "label": "Secondary Print Fan Speed",
                    "description": "The speed at which the secondary print cooling fans spin. The secondary fans speed is relative to the primary cooling fan speed.",
                    "type": "float",
                    "enabled": "blackbelt_secondary_fans_enabled",
                    "unit": "%",
                    "type": "float",
                    "minimum_value": "0",
                    "default_value": 100,
                    "settable_per_mesh": false,
                    "settable_per_extruder": true
                }
            }
        },
        "machine_settings": {
            "children":
            {
                "blackbelt_gantry_angle":
                {
                    "label": "Gantry Angle",
                    "description": "The angle of the gantry relative to the build plate. Match this setting with the current printer configuration.",
                    "unit": "°",
                    "type": "enum",
                    "options":
                    {
                        "15": "15°",
                        "25": "25°",
                        "35": "35°",
                        "45": "45°"
                    },
                    "default_value": "45",
                    "settable_per_mesh": false,
                    "settable_per_extruder": false
                },
                "blackbelt_z_offset":
                {
                    "label": "Belt Offset",
                    "description": "The offset to the belt (0.1 = big gap, 0.3 = small gap)",
                    "type": "float",
                    "unit": "mm",
                    "default_value": 0.2,
                    "value": "round((wall_line_width_0 / 2) - (blackbelt_z_offset_gap / math.sin(math.radians(float(blackbelt_gantry_angle)))) - xy_offset, 4)",
                    "maximum_value_warning": "machine_nozzle_size",
                    "settable_per_mesh": false,
                    "settable_per_extruder": false
                },
                "blackbelt_repetitions_gcode":
                {
                    "label": "Repetitions GCode",
                    "description": "Gcode commands to be executed between repetitions - separated by \\n.",
                    "type": "str",
                    "default_value": "\nG92 E0   ; Set Extruder to zero\nG1 E-4 F3900  ; Retract 4mm at 65mm/s\nG92 Z0   ; Set Belt to zero\nG1 Z{blackbelt_repetitions_distance}   ; Advance belt between repetitions\nG92 Z0   ; Set Belt to zero again\n\n;˄˄˄˄˄˄˄˄˄˄˄˄˄˄˄˄ - repetition - ˄˄˄˄˄˄˄˄˄˄˄˄˄˄˄˄\n\nM107    ; Start with the fan off\nG0 X170 ; Move X to the center\nG1 Y1   ; Move y to the belt\nG1 E0   ; Move extruder back to 0\nG92 E-5 ; Add 5mm restart distance\n\n",
                    "enabled": "blackbelt_repetitions > 1",
                    "settable_per_mesh": false,
                    "settable_per_extruder": false
                }
            }
        }
    },

    "overrides": {
        "machine_name": {
            "default_value": "BLACKBELT 3D Printer"
        },
        "machine_start_gcode" : {
            "default_value": "G90               ; Set to Absolute Positioning\nM82               ; Set extruder to absolute mode\nG21               ; Metric values\nG92 X0 Y0 Z0 E0   ; Set all axis to 0\n;home X\nG1 Y2             ; Move Y axis off the bed\nG28 X0 F2000      ; Home X axis\nG1 X170 F4000     ; Move X to the center\n;probe Y\nM908 P5 S10       ; Setting the motor current of the Y1 motor off\nM908 P1 S10       ; Setting the motor current of the Y2 motor off\nG1 Y20 G3000      ; Move Y up\nM400              ; Wait for current moves to finish\nM908 P5 S30       ; Setting the motor current of the Y1 motor very low\nM908 P1 S30       ; Setting the motor current of the Y2 motor off\nG1 Y0 F500        ; Move Y down into the belt\nM400              ; Wait for current moves to finish\nM908 P5 S140      ; Setting the motor current of the Y1 motor to normal\nM908 P1 S140      ; Setting the motor current of the Y2 motor to normal\nG92 Y{blackbelt_z_offset}\n;purge\nG1 F15000         ; Set high feedrate\nG1 X170 F10000    ; Move the print head to the center and break the melt\nG1 X335 Y 1 G1 E10; Extruder 10mm material and move to the side\nG1 E15            ; Extrude 5mm more\nG1 Z5 E18 F500    ; Move belt 5mm and keep extruding\nG1 Z30            ; Move the belt a bit further without extruding\nG92 Z0            ; Zero Belt\nG92 E0            ; Zero the extruded length\nG1 E-4 F3900      ; Retract 4mm at 65mm/s\n;prepare printing\nG1 X170 F15000    ; Move the print head to the center and break the melt\nG1 Y{blackbelt_z_offset}    ; Move y to the belt\nG1 E0             ; Move extruder back to 0\nG92 E-1           ; Add 1mm start distance\nM117 BLACKBELT Printing...\n\n;˅˅˅˅˅˅˅˅˅˅˅˅˅˅˅˅ - copy from here / paste codes just under here - ˅˅˅˅˅˅˅˅˅˅˅˅˅˅˅˅\nM107              ; Start with the fan off"
        },
        "machine_end_gcode" : {
            "default_value": "G92 E0   ; Set Extruder to zero\nG1 E-6   ; Retract 6mm\nG92 Z0   ; Set Belt to zero\nG1 Z{blackbelt_repetitions_distance}   ; Move Belt 15mm before starting up the next product\nG92 Z0   ; Set Belt to zero again\n\n;˄˄˄˄˄˄˄˄˄˄˄˄˄˄˄˄ - copy up to here / paste codes just above here - ˄˄˄˄˄˄˄˄˄˄˄˄˄˄˄˄\nM104 S0  ; Extruder heater off\nM140 S0  ; Heated bed heater off\nG92 Z0\nG1 Z10 F1000\nG28 X0 F2000\nG1 Z20 F1000\nG1 X170 F2000\nG1 Y{blackbelt_z_offset} F2000\nM18      ; Disable all stepper motors"
        },
        "machine_width": {
            "default_value": 340
        },
        "machine_height": {
            "default_value": 340,
            "value": "485 * math.sin(math.radians(float(blackbelt_gantry_angle)))"
        },
        "machine_depth": {
            "default_value": 99999
        },
        "material_diameter": {
            "default_value": 1.75
        },
        "machine_gcode_flavor": {
            "default_value": "RepRap (Marlin/Sprinter)"
        },
        "machine_heated_bed": {
            "default_value": true
        },

        "support_enable": {
            "enabled": false,
            "default_value": true,
            "settable_per_mesh": false
        },
        "support_angle": {
            "enabled": false,
            "default_value": 90
        },
        "support_type": {
            "enabled": false
        },
        "gradual_support_infill_steps": {
            "enabled": false
        },
        "support_interface_enable": {
            "enabled": false
        },
        "support_roof_enable": {
            "enabled": false
        },
        "support_bottom_enable": {
            "enabled": false
        },
        "support_use_towers": {
            "enabled": false
        },
        "support_tree_enable": {
            "enabled": false,
            "settable_per_mesh": false
        },
        "support_tree_branch_distance": {
            "enabled": false,
            "settable_per_mesh": false
        },
        "remove_empty_first_layers": {
            "enabled": false
        },
        "support_mesh_drop_down": {
            "enabled": false,
            "default_value": false
        },
        "anti_overhang_mesh": {
            "enabled": false
        },
        "adhesion_type": {
            "enabled": false,
            "value": "'raft' if blackbelt_raft else 'none'"
        },
        "raft_margin": {
            "default_value": 0,
            "enabled": false
        },
        "raft_surface_layers": {
            "default_value": 0,
            "enabled": false
        },
        "layer_0_z_overlap": {
            "default_value": 0,
            "enabled": false
        },
        "raft_base_thickness":
        {
            "value": "blackbelt_raft_thickness",
            "enabled": false
        },
        "raft_airgap":
        {
            "value": "blackbelt_raft_gap",
            "enabled": false
        },

        "raft_smoothing":
        {
            "enabled": false
        },
        "raft_surface_thickness":
        {
            "enabled": false
        },
        "raft_surface_line_width":
        {
            "enabled": false
        },
        "raft_surface_line_spacing":
        {
            "enabled": false
        },
        "raft_interface_thickness":
        {
            "enabled": false
        },
        "raft_interface_line_width":
        {
            "enabled": false
        },
        "raft_interface_line_spacing":
        {
            "enabled": false
        },
        "raft_base_line_width":
        {
            "enabled": false
        },
        "raft_base_line_spacing":
        {
            "enabled": false
        },
        "raft_speed":
        {
            "enabled": false
        },
        "raft_surface_speed":
        {
            "enabled": false
        },
        "raft_interface_speed":
        {
            "enabled": false
        },
        "raft_base_speed":
        {
            "enabled": false
        },
        "raft_acceleration":
        {
            "enabled": false
        },
        "raft_surface_acceleration":
        {
            "enabled": false
        },
        "raft_interface_acceleration":
        {
            "enabled": false
        },
        "raft_base_acceleration":
        {
            "enabled": false
        },
        "raft_jerk":
        {
            "enabled": false
        },
        "raft_surface_jerk":
        {
            "enabled": false
        },
        "raft_interface_jerk":
        {
            "enabled": false
        },
        "raft_base_jerk":
        {
            "enabled": false
        },
        "raft_fan_speed":
        {
            "enabled": false
        },
        "raft_surface_fan_speed":
        {
            "enabled": false
        },
        "raft_interface_fan_speed":
        {
            "enabled": false
        },
        "raft_base_fan_speed":
        {
            "enabled": false
        },

        "relative_extrusion":
        {
            "enabled": false
        },

        "z_offset_layer_0": {
            "enabled": false
        },
        "print_sequence": {
            "enabled": false
        },
        "top_bottom_pattern_0": {
            "enabled": false
        },
        "infill_pattern":
        {
            "options":
            {
                "grid": "Grid",
                "lines": "Lines",
                "triangles": "Triangles",
                "cubic": "Cubic",
                "cubicsubdiv": "Cubic Subdivision",
                "tetrahedral": "Octet",
                "quarter_cubic": "Quarter Cubic",
                "zigzag": "Zig Zag",
                "cross": "Cross",
                "cross_3d": "Cross 3D"
            },
            "value": "'lines'"
        },
        "infill_angles":
        {
            "value": "'[' + str(round(45 * math.sin(math.radians(float(blackbelt_gantry_angle))))) + ',-' + str(round(45 * math.sin(math.radians(float(blackbelt_gantry_angle))))) + ']' if infill_pattern == 'lines' else '[ ]'"
        },
        "infill_line_distance":
        {
            "minimum_value_warning": "0 if infill_sparse_density == 0 else infill_line_width"
        },
        "travel_avoid_other_parts":
        {
            "default_value": false
        },
        "max_feedrate_z_override":
        {
            "enabled": false
        },
        "ooze_shield_enabled":
        {
            "enabled": false
        },
        "draft_shield_enabled":
        {
            "enabled": false
        },
        "conical_overhang_enabled":
        {
            "enabled": false
        },
        "support_conical_enabled":
        {
            "settable_per_mesh": false
        },
        "support_conical_angle":
        {
            "settable_per_mesh": false
        },
        "support_conical_min_width":
        {
            "settable_per_mesh": false
        },
        "switch_extruder_retraction_amount":
        {
            "enabled": false
        },
        "switch_extruder_retraction_speeds":
        {
            "enabled": false
        },
        "mold_enabled":
        {
            "enabled": false
        },
        "magic_fuzzy_skin_enabled":
        {
            "enabled": false
        },
        "wireframe_enabled": {
            "enabled": false
        },

        "layer_height_0": {
            "enabled": false,
            "value": "layer_height"
        },
        "top_bottom_pattern_0": {
            "enabled": false
        },
        "xy_offset_layer_0": {
            "enabled": false
        },
        "initial_layer_line_width_factor": {
            "enabled": false
        },
        "line_width": {
            "value": "machine_nozzle_size"
        },
        "wall_line_width": {
            "value": "line_width"
        },
        "wall_line_width_0": {
            "value": "line_width + 0.1"
        },
        "skin_line_width": {
            "value": "line_width"
        },
        "infill_line_width": {
            "value": "line_width + 0.2"
        },
        "skin_preshrink": {
            "value": "2"
        },
        "expand_skins_expand_distance": {
            "value": "0"
        },
        "retraction_extrusion_window": {
            "value": "3"
        },
        "retraction_min_travel": {
            "value": "0.8"
        },
        "z_seam_type": {
            "value": "'shortest'"
        }
    }
}
