{

    "name": "Proton X Rod",
    "version": 2,
    "inherits": "inat_base",
    "metadata": {
        "visible": true,
        "quality_definition": "inat_base",
        "platform": "inat_proton_x_buildplate.stl",
        "platform_offset": [ 0, 0, 0]
    },
    "overrides": {
        "machine_name": { "value": "Proton X" },
        "machine_width": { "value": 304 },
        "machine_depth": { "value": 304 },
        "machine_height": { "value": 650 },
        "machine_head_with_fans_polygon": {
            "value": [
                [
                    -86,
                    66
                ],
                [
                    44,
                    66
                ],
                [
                    44,
                    -96
                ],
                [
                    -86,
                    -96
                ]
            ]
        },

        "gantry_height": { "value": 34 }

    }
}